{
  "$type": "IronStar.Mapping.Map, IronStar",
  "Environment": {
    "$type": "IronStar.Mapping.MapEnvironment, IronStar",
    "Gravity": 48.0,
    "SkyTrubidity": 2.0,
    "SunAltitude": 39.0,
    "SkyIntensity": 1.0,
    "SunAzimuth": 60.0,
    "SunIntensity": 500.0,
    "FogDistance": 500000.0,
    "FogHeight": 0.05,
    "FogColor": "10, 10, 10, 0"
  },
  "Nodes": {
    "$type": "IronStar.Mapping.MapNodeCollection, IronStar",
    "$values": [
      {
        "$type": "IronStar.Mapping.MapModel, IronStar",
        "NodeGuid": "a94e45b9-aae8-46f3-8d3a-e3fb3629c953",
        "ScenePath": "scenes\\grayBoxing\\lightMapTest.fbx",
        "Scale": 1.0,
        "GlowColor": "255, 0, 0, 255",
        "GlowIntensity": 100.0,
        "LightMapSize": "lightMap512",
        "UseLightVolume": false,
        "UseCollisionMesh": false,
        "UseCustomNodes": false,
        "CustomVisibleNode": "",
        "CustomCollisionNode": "",
        "Visible": true,
        "Frozen": false,
        "TranslateX": 0.0,
        "TranslateY": 0.0,
        "TranslateZ": 0.0,
        "RotateYaw": 0.0,
        "RotatePitch": 0.0,
        "RotateRoll": 0.0
      },
      {
        "$type": "IronStar.Mapping.MapEntity, IronStar",
        "NodeGuid": "a6819d03-460b-4673-a744-5e7b3fa56c89",
        "TargetName": null,
        "Factory": {
          "$type": "IronStar.Entities.StartPointFactory, IronStar",
          "StartPointType": "singlePlayer"
        },
        "FactoryName": "YTd2a4Rx",
        "Visible": true,
        "Frozen": false,
        "TranslateX": 0.0,
        "TranslateY": 0.0,
        "TranslateZ": -12.0,
        "RotateYaw": 0.0,
        "RotatePitch": 0.0,
        "RotateRoll": 0.0
      }
    ]
  },
  "RadiositySettings": {
    "$type": "Fusion.Engine.Graphics.GI.RadiositySettings, Fusion",
    "LightGridWidth": 32,
    "LightGridHeight": 16,
    "LightGridDepth": 32,
    "LightGridStep": 16.0,
    "NormalOffsetBias": 0.25,
    "LightMapSampleCount": 128,
    "LightGridSampleCount": 64,
    "MaxPatches": 32,
    "RadianceThreshold": 0.02,
    "DebugLightmaps": true
  }
}